instacapture/InstaPost.py
instacapture/InstaStory.py
instacapture/__init__.py
tests/__init__.py
tests/test_simple.py
instacapture-0.2.0.dist-info/LICENSE
instacapture-0.2.0.dist-info/METADATA
instacapture-0.2.0.dist-info/WHEEL
instacapture-0.2.0.dist-info/top_level.txt
instacapture-0.2.0.dist-info/RECORD
