Metadata-Version: 2.1
Name: instacapture
Version: 0.2.0
Summary: A Python package for downloading Instagram stories, posts, reels, IGTV videos, and profile pictures
Home-page: https://github.com/prathmeshsoni/InstaCapture
Author: Prathmesh Soni
Author-email: info@soniprathmesh.com
License: MIT
Keywords: Instagram downloader stories reels posts
Classifier: Development Status :: 4 - Beta
Classifier: Intended Audience :: Developers
Classifier: Programming Language :: Python :: 3
Classifier: Programming Language :: Python :: 3.6
Classifier: Programming Language :: Python :: 3.7
Classifier: Programming Language :: Python :: 3.8
Classifier: Programming Language :: Python :: 3.9
Classifier: Programming Language :: Python :: 3.10
Classifier: License :: OSI Approved :: MIT License
Classifier: Operating System :: OS Independent
Classifier: Topic :: Software Development :: Libraries :: Python Modules
Requires-Python: >=3.6
License-File: LICENSE
Requires-Dist: pytz
Requires-Dist: requests
Requires-Dist: lxml
